kapla/__init__.py
kapla/__main__.py
kapla/py.typed
kapla/cli/__init__.py
kapla/cli/app.py
kapla/cli/build.py
kapla/cli/install.py
kapla/cli/licenses.py
kapla/cli/list.py
kapla/cli/project.py
kapla/cli/repair.py
kapla/cli/run.py
kapla/cli/uninstall.py
kapla/cli/venv.py
kapla/core/__init__.py
kapla/core/cmd.py
kapla/core/errors.py
kapla/core/finder.py
kapla/core/io.py
kapla/core/logger.py
kapla/core/templates.py
kapla/core/timeout.py
kapla/core/windows.py
kapla/projects/__init__.py
kapla/projects/base.py
kapla/projects/kproject.py
kapla/projects/krepo.py
kapla/projects/pyproject.py
kapla/specs/__init__.py
kapla/specs/base.py
kapla/specs/common.py
kapla/specs/kproject.py
kapla/specs/lock.py
kapla/specs/pyproject.py
kapla/specs/repo.py
kapla/wrappers/__init__.py
kapla/wrappers/git.py
kapla/wrappers/poetry.py
kapla_cli_v2-0.32.0.dist-info/METADATA
kapla_cli_v2-0.32.0.dist-info/WHEEL
kapla_cli_v2-0.32.0.dist-info/entry_points.txt
kapla_cli_v2-0.32.0.dist-info/top_level.txt
kapla_cli_v2-0.32.0.dist-info/RECORD
