Metadata-Version: 2.1
Name: kapla-cli-v2
Version: 0.32.0
Summary: Python monorepo package manager
Author-email: Guillaume Charbonnier <guillaume.charbonnier@araymond.com>
License: Apache-2.0
Project-URL: Repository, https://github.com/charbonnierg/kapla-cli-v2
Project-URL: Issues, https://github.com/charbonnierg/kapla-cli-v2/issues
Keywords: nats,nats-server
Classifier: Programming Language :: Python :: 3
Classifier: License :: OSI Approved :: Apache Software License
Requires-Python: >=3.7
Requires-Dist: pydantic <2
Requires-Dist: anyio
Requires-Dist: ruamel.yaml
Requires-Dist: tomlkit
Requires-Dist: rich
Requires-Dist: structlog
Requires-Dist: chardet
Requires-Dist: Jinja2
Requires-Dist: graphlib-backport ; python_version < "3.9"
Provides-Extra: dev
Requires-Dist: black ; extra == 'dev'
Requires-Dist: isort ; extra == 'dev'
Requires-Dist: flake8 ; extra == 'dev'
Requires-Dist: mypy ; extra == 'dev'
Requires-Dist: types-toml ; extra == 'dev'
Requires-Dist: types-setuptools ; extra == 'dev'
Requires-Dist: types-chardet ; extra == 'dev'
Provides-Extra: tests
Requires-Dist: pytest ; extra == 'tests'
Requires-Dist: pytest-cov ; extra == 'tests'
